EJ1/Verilog/modules/fsm_sequence_gates.v
//--------------------------------------------------------------------------------
// Module: fsm_sequence
//
// Implementation for a fsm that commands two pumps B1 and B2, given the signals 
// of two sensors I (lower) and S (upper) that are high when water in a tank 
// reaches their level.
// This module uses a behavioral pattern/style for the module's code.
// It is a Mealy Machine.
//--------------------------------------------------------------------------------

module fsm_sequence(
    clock,              // Clock input of the synchronous sequential design
    reset,              // Active high, synchronous reset input
    level_sensors,      // Input sensors for the fsm
    pumps,              // Output controlling the pumps
    next_state,         // Next state, for debugging
    current_state      // Current state, for debugging
);

    //----------------- INPUT PORTS -----------------------------
    input wire clock;
    input wire reset;
    input wire [1:0] level_sensors;  // First bit is I sensor, second bit is S sensor

    //----------------- OUTPUT PORTS ----------------------------
    output wire [1:0] pumps;         // First bit is B1 pump, second bit is B2 pump
    output wire next_state;
    output wire current_state;

    //----------------- INTERNAL VARIABLES ----------------------

    //----------------- MODULE INSTANCES ------------------------
    fsm_next_state my_next_state(current_state, level_sensors, next_state);
    flip_flop_d my_ffd(next_state, reset, clock, current_state);
    fsm_output_B1 my_B1(current_state, level_sensors, pumps[0]);
    fsm_output_B2 my_B2(current_state, level_sensors, pumps[1]);


endmodule

//------------------------------------------------------------
// Module: fsm_next_state
//
// Combinational logic to determine the next state of the fsm
//------------------------------------------------------------

module fsm_next_state(
    current_state,  // Current state of the fsm
    in,             // Current input of the fsm
    next_state      // Next state of the fsm, output
);

    //----------------- INPUT PORTS -----------------------
    input wire current_state;
    input wire [1:0] in;

    //----------------- OUTPUT PORTS ----------------------
    output wire next_state;

    /* Output gate connection */
    assign next_state = (~(in[1] ^ current_state) & ~in[0]) | ((in[1] ^ current_state) & in[0]);

endmodule

//--------------------------------------------------
// Module: fsm_output
//
// Combinational logic to set the output B1 of the fsm
//---------------------------------------------------

module fsm_output_B1(
    current_state,  // Current state of the fsm
    in,     // Current input of the fsm
    B1      // Output of the fsm
);

    //----------------- INPUT PORTS -----------------------
    input wire current_state;
    input wire [1:0] in;

    //----------------- OUTPUT PORTS ----------------------
    output wire B1;

    /* Output gate connection */
    assign B1 = (~in[1] & ~in[0]) | (~(in[1] | current_state) & in[0]);

endmodule

//--------------------------------------------------
// Module: fsm_output
//
// Combinational logic to set the output B2 of the fsm
//---------------------------------------------------

module fsm_output_B2(
    current_state,  // Current state of the fsm
    in,     // Current input of the fsm
    B2      // Output of the fsm
);

    //----------------- INPUT PORTS -----------------------
    input wire current_state;
    input wire [1:0] in;

    //----------------- OUTPUT PORTS ----------------------
    output wire B2;

    /* Output gate connection */
    assign B2 = (~in[1] & ~in[0]) | ((~in[1] & current_state) & in[0]);

endmodule

EJ1/Verilog/standard_modules/flip_flop_d.v
//-------------------------------------
// Module: flip_flop_d
//
// Flip Flop D with asynchronous reset
//-------------------------------------

module flip_flop_d(
    d,      // Flip Flop D input
    reset,  // High level asynchronous reset
    clk,    // Clock
    q       // Output
);

    // Input Port declaration
    input wire reset;
    input wire clk;
    input wire d;

    // Output Port declaration
    output reg q;
    
    initial begin
        q = 0;
    end

    always @(posedge clk or reset) begin
        if (reset) begin
            q = 0; 
        end else begin
            q = d;
        end
    end
endmodule

EJ1/Verilog/standard_modules/clock_gen.v
//----------------------------
// Module: clock_gen
//
//
// Generates a clock waveform
//----------------------------
`timescale 100us / 100us


module clock_gen(
    clk
);
    // Output Port declaration
    output reg clk;

    // Auxiliar declarations
    parameter PERIOD = 2;

    initial begin: INITIALIZE
        clk = 0;
    end

    always begin: CLOCK_GENERATION
        #(PERIOD/2);
        clk = ~clk;
    end

endmodule

EJ1/Verilog/tests/fsm_sequence_test.v
//---------------------------------------
// Module: fsm_sequence_test
//
// Testbench of the fsm_sequence module.
//---------------------------------------

// Using the timescale directive to be used in the ticks
`timescale 100us / 100us

module fsm_sequence_test();

    //----------------- INTERNAL VARIABLES ---------------------
    wire clock;
    reg [1:0] sensors;
    reg reset;
    wire [1:0] pumps;

    wire next_state;
    wire current_state;

    integer count;
    integer i;

    //----------------- CONSTANT VALUES -----------------------
    parameter BIT_MASK = 4'b1000;
    
    //----------------- MODULE INSTANCES -----------------------
    clock_gen #(.PERIOD(2)) my_clk(clock);
    fsm_sequence my_fsm(clock, reset, sensors, pumps, next_state, current_state);

    /* ¡Testing code! */
    initial begin: TESTING
        sensors = 2'b00;
        #2 reset = 1;
        #2 reset = 0;
        #2 $display("Testing I=0 S=0. Output: %b%b. Next state is %b. Current state is %b", pumps[1], pumps[0], next_state, current_state);

        #2 sensors = 2'b01;
        #2 
        #2 $display("Testing I=1 S=0. Output: %b%b. Next state is %b. Current state is %b", pumps[1], pumps[0], next_state, current_state);

        #2 sensors = 2'b11;
        #2 
        #2 $display("Testing I=1 S=1. Output: %b%b. Next state is %b. Current state is %b", pumps[1], pumps[0], next_state, current_state);

        #2 sensors = 2'b01;
        #2 
        #2 $display("Testing I=1 S=0. Output: %b%b. Next state is %b. Current state is %b", pumps[1], pumps[0], next_state, current_state);
        
        #2 sensors = 2'b00;
        #2 
        #2 $display("Testing I=0 S=0. Output: %b%b. Next state is %b. Current state is %b", pumps[1], pumps[0], next_state, current_state);
        
        #2 sensors = 2'b01;
        #2 
        #2 $display("Testing I=1 S=0. Output: %b%b. Next state is %b. Current state is %b", pumps[1], pumps[0], next_state, current_state);
        
        #2 sensors = 2'b00;
        #2 
        #2 $display("Testing I=0 S=0. Output: %b%b. Next state is %b. Current state is %b", pumps[1], pumps[0], next_state, current_state);
        
        #2 sensors = 2'b11;
        #2 
        #2 $display("Testing I=1 S=1. Output: %b%b. Next state is %b. Current state is %b", pumps[1], pumps[0], next_state, current_state);
        
        #2 sensors = 2'b01;
        #2 
        #2 $display("Testing I=1 S=0. Output: %b%b. Next state is %b. Current state is %b", pumps[1], pumps[0], next_state, current_state);
        
        #2 sensors = 2'b10;
        #2 
        #2 $display("Testing impossible situation. Output: %b%b. Next state is %b. Current state is %b", pumps[1], pumps[0], next_state, current_state);
        
        #2 sensors = 2'b01;
        #2 
        #2 $display("Testing I=1 S=0. Output: %b%b. Next state is %b. Current state is %b", pumps[1], pumps[0], next_state, current_state);

        #5

        $finish;
    end

    /* ¡Creating GTKWave File! */
    initial begin: GTKWAVE_FILE
        $dumpfile("bin/output.vcd");
        $dumpvars(0, fsm_sequence_test);
    end
endmodule

EJ1/Verilog/bin/output.vcd
$date
	Sun Nov 10 18:36:53 2019
$end
$version
	Icarus Verilog
$end
$timescale
	100us
$end
$scope module fsm_sequence_test $end
$var wire 2 ! pumps [1:0] $end
$var wire 1 " next_state $end
$var wire 1 # current_state $end
$var wire 1 $ clock $end
$var reg 1 % reset $end
$var reg 2 & sensors [1:0] $end
$scope module my_clk $end
$var reg 1 $ clk $end
$scope begin CLOCK_GENERATION $end
$upscope $end
$scope begin INITIALIZE $end
$upscope $end
$upscope $end
$scope module my_fsm $end
$var wire 1 $ clock $end
$var wire 2 ' level_sensors [1:0] $end
$var wire 1 % reset $end
$var wire 2 ( pumps [1:0] $end
$var wire 1 " next_state $end
$var wire 1 # current_state $end
$scope module my_B1 $end
$var wire 1 ) B1 $end
$var wire 2 * in [1:0] $end
$var wire 1 # current_state $end
$upscope $end
$scope module my_B2 $end
$var wire 1 + B2 $end
$var wire 2 , in [1:0] $end
$var wire 1 # current_state $end
$upscope $end
$scope module my_ffd $end
$var wire 1 $ clk $end
$var wire 1 % reset $end
$var wire 1 " d $end
$var reg 1 # q $end
$upscope $end
$scope module my_next_state $end
$var wire 1 # current_state $end
$var wire 2 - in [1:0] $end
$var wire 1 " next_state $end
$upscope $end
$upscope $end
$scope begin GTKWAVE_FILE $end
$upscope $end
$scope begin TESTING $end
$upscope $end
$upscope $end
$enddefinitions $end
#0
$dumpvars
b0 -
b0 ,
1+
b0 *
1)
b11 (
b0 '
b0 &
x%
0$
0#
1"
b11 !
$end
#1
0"
1#
1$
#2
1"
0#
0$
1%
#3
1$
#4
0"
1#
0$
0%
#5
1"
0#
1$
#6
0$
#7
0"
1#
1$
#8
b10 !
b10 (
0)
1"
0$
b1 &
b1 '
b1 *
b1 ,
b1 -
#9
1$
#10
0$
#11
1$
#12
0$
#13
1$
#14
b0 !
b0 (
0+
0"
0$
b11 &
b11 '
b11 *
b11 ,
b11 -
#15
1"
0#
1$
#16
0$
#17
0"
1#
1$
#18
0$
#19
1"
0#
1$
#20
b1 !
b1 (
1)
0"
0$
b1 &
b1 '
b1 *
b1 ,
b1 -
#21
1$
#22
0$
#23
1$
#24
0$
#25
1$
#26
1+
1"
b11 !
b11 (
1)
0$
b0 &
b0 '
b0 *
b0 ,
b0 -
#27
0"
1#
1$
#28
0$
#29
1"
0#
1$
#30
0$
#31
0"
1#
1$
#32
b10 !
b10 (
0)
1"
0$
b1 &
b1 '
b1 *
b1 ,
b1 -
#33
1$
#34
0$
#35
1$
#36
0$
#37
1$
#38
1)
b11 !
b11 (
1+
0"
0$
b0 &
b0 '
b0 *
b0 ,
b0 -
#39
1"
0#
1$
#40
0$
#41
0"
1#
1$
#42
0$
#43
1"
0#
1$
#44
0)
b0 !
b0 (
0+
0$
b11 &
b11 '
b11 *
b11 ,
b11 -
#45
0"
1#
1$
#46
0$
#47
1"
0#
1$
#48
0$
#49
0"
1#
1$
#50
b10 !
b10 (
1+
1"
0$
b1 &
b1 '
b1 *
b1 ,
b1 -
#51
1$
#52
0$
#53
1$
#54
0$
#55
1$
#56
b0 !
b0 (
0+
1"
0$
b10 &
b10 '
b10 *
b10 ,
b10 -
#57
1$
#58
0$
#59
1$
#60
0$
#61
1$
#62
b10 !
b10 (
1+
0$
b1 &
b1 '
b1 *
b1 ,
b1 -
