EJ1/Verilog/modules/fsm_sequence_gates.v
//--------------------------------------------------------------------------------
// Module: fsm_sequence
//
// Implementation for a fsm that detects a serial sequence of bits 1-1-0-1, 
// using a behavioral pattern/style for the module's code. It is a Mealy Machine.
//--------------------------------------------------------------------------------

module fsm_sequence(
    clock,  // Clock input of the synchronous sequential design
    reset,  // Active high, synchronous reset input
    w,      // Serial sequence of input bits
    z       // Output of the fsm
);

    //----------------- INPUT PORTS -----------------------------
    input wire clock;
    input wire reset;
    input wire w;

    //----------------- OUTPUT PORTS ----------------------------
    output wire z;

    //----------------- INTERNAL VARIABLES ----------------------
    wire [1:0] current_state;
    wire [1:0] next_state;

    //----------------- MODULE INSTANCES ------------------------
    fsm_next_state u_next_state(current_state, w, next_state);
    flip_flop_d u_ffd_0(next_state[0], reset, clock, current_state[0]);
    flip_flop_d u_ffd_1(next_state[1], reset, clock, current_state[1]);
    fsm_output u_output(current_state, w, z);


endmodule

//------------------------------------------------------------
// Module: fsm_next_state
//
// Combinational logic to determine the next state of the fsm
//------------------------------------------------------------

module fsm_next_state(
    current_state,  // Current state of the fsm
    in,             // Current input of the fsm
    next_state      // Next state of the fsm, output
);

    //----------------- INPUT PORTS -----------------------
    input wire [1:0] current_state;
    input wire in;

    //----------------- OUTPUT PORTS ----------------------
    output wire [1:0] next_state;

    /* Next state connection */
    assign next_state[1] = ~in | current_state[1] & ~current_state[0];
    assign next_state[0] = ~current_state[0] |   in ^ current_state[1];

endmodule

//--------------------------------------------------
// Module: fsm_output
//
// Combinational logic to set the output of the fsm
//---------------------------------------------------

module fsm_output(
    state,  // Current state of the fsm
    in,     // Current input of the fsm
    z       // Output of the fsm
);

    //----------------- INPUT PORTS -----------------------
    input wire [1:0] state;
    input wire in;

    //----------------- OUTPUT PORTS ----------------------
    output wire z;

    /* Output gate connection */
    assign z = in & state[1] & ~state[0];

endmodule

EJ1/Verilog/standard_modules/flip_flop_d.v
//-------------------------------------
// Module: flip_flop_d
//
// Flip Flop D with asynchronous reset
//-------------------------------------

module flip_flop_d(
    d,      // Flip Flop D input
    reset,  // High level asynchronous reset
    clk,    // Clock
    q       // Output
);

    // Input Port declaration
    input wire reset;
    input wire clk;
    input wire d;

    // Output Port declaration
    output reg q;
    
    initial begin
        q = 0;
    end

    always @(posedge clk or reset) begin
        if (reset) begin
            q = 0; 
        end else begin
            q = d;
        end
    end
endmodule

EJ1/Verilog/standard_modules/clock_gen.v
//----------------------------
// Module: clock_gen
//
//
// Generates a clock waveform
//----------------------------
`timescale 100us / 100us


module clock_gen(
    clk
);
    // Output Port declaration
    output reg clk;

    // Auxiliar declarations
    parameter PERIOD = 2;

    initial begin: INITIALIZE
        clk = 0;
    end

    always begin: CLOCK_GENERATION
        #(PERIOD/2);
        clk = ~clk;
    end

endmodule

EJ1/Verilog/tests/fsm_sequence_test.v
//---------------------------------------
// Module: fsm_sequence_test
//
// Testbench of the fsm_sequence module.
//---------------------------------------

// Using the timescale directive to be used in the ticks
`timescale 100us / 100us

module fsm_sequence_test();

    //----------------- INTERNAL VARIABLES ---------------------
    wire clock;
    wire z;

    reg reset;
    reg w;

    integer count;
    integer i;

    //----------------- CONSTANT VALUES -----------------------
    parameter BIT_MASK = 4'b1000;
    
    //----------------- MODULE INSTANCES -----------------------
    clock_gen #(.PERIOD(2)) u_clk(clock);
    fsm_sequence u_fsm(clock, reset, w, z);

    /* ¡Testing code! */
    initial begin: TESTING
        w = 0;
        #2 reset = 1;
        #2 reset = 0;

        #2 w = 0;
        #2 w = 1;
        #2 w = 0;
        #2 $display("Testing 0-1-0. Output: %b", z);

        #2 w = 1;
        #2 w = 1;
        #2 w = 1;
        #2 w = 0;
        #2 w = 0;
        #2 $display("Testing 1-1-1-0-0. Output: %b", z);

        #2 w = 1;
        #2 w = 1;
        #2 w = 0;
        #2 w = 1;
        #1 $display("Testing 1-1-0-1. Output: %b", z);
        #5

        $finish;
    end

    /* ¡Creating GTKWave File! */
    initial begin: GTKWAVE_FILE
        $dumpfile("bin/output.vcd");
        $dumpvars(0, fsm_sequence_test);
    end
endmodule

EJ1/Verilog/bin/output.vcd
$date
	Sun Nov 10 14:25:37 2019
$end
$version
	Icarus Verilog
$end
$timescale
	100us
$end
$scope module fsm_sequence_test $end
$var wire 1 ! z $end
$var wire 1 " clock $end
$var reg 1 # reset $end
$var reg 1 $ w $end
$scope module u_clk $end
$var reg 1 " clk $end
$scope begin CLOCK_GENERATION $end
$upscope $end
$scope begin INITIALIZE $end
$upscope $end
$upscope $end
$scope module u_fsm $end
$var wire 1 " clock $end
$var wire 1 # reset $end
$var wire 1 $ w $end
$var wire 1 ! z $end
$var wire 2 % next_state [1:0] $end
$var wire 2 & current_state [1:0] $end
$scope module u_ffd_0 $end
$var wire 1 " clk $end
$var wire 1 ' d $end
$var wire 1 # reset $end
$var reg 1 ( q $end
$upscope $end
$scope module u_ffd_1 $end
$var wire 1 " clk $end
$var wire 1 ) d $end
$var wire 1 # reset $end
$var reg 1 * q $end
$upscope $end
$scope module u_next_state $end
$var wire 2 + current_state [1:0] $end
$var wire 1 $ in $end
$var wire 2 , next_state [1:0] $end
$upscope $end
$scope module u_output $end
$var wire 1 $ in $end
$var wire 2 - state [1:0] $end
$var wire 1 ! z $end
$upscope $end
$upscope $end
$scope begin GTKWAVE_FILE $end
$upscope $end
$scope begin TESTING $end
$upscope $end
$upscope $end
$enddefinitions $end
#0
$dumpvars
b0 -
b11 ,
b0 +
0*
1)
0(
1'
b0 &
b11 %
0$
x#
0"
0!
$end
#1
1(
b11 &
b11 +
b11 -
1*
1"
#2
0*
b0 &
b0 +
b0 -
0(
0"
1#
#3
1"
#4
1*
b11 &
b11 +
b11 -
1(
0"
0#
#5
1"
#6
0"
#7
1"
#8
0)
0'
b0 %
b0 ,
0"
1$
#9
1'
b1 %
b1 ,
0(
b0 &
b0 +
b0 -
0*
1"
#10
1)
b11 %
b11 ,
0"
0$
#11
1*
b11 &
b11 +
b11 -
1(
1"
#12
0"
#13
1"
#14
0)
0'
b0 %
b0 ,
0"
1$
#15
1'
b1 %
b1 ,
0*
b0 &
b0 +
b0 -
0(
1"
#16
0"
#17
b1 &
b1 +
b1 -
1(
1"
#18
0"
#19
1"
#20
1)
0'
b10 %
b10 ,
0"
0$
#21
1'
b11 %
b11 ,
0(
b10 &
b10 +
b10 -
1*
1"
#22
0"
#23
b11 &
b11 +
b11 -
1(
1"
#24
0"
#25
1"
#26
0)
0'
b0 %
b0 ,
0"
1$
#27
1'
b1 %
b1 ,
0*
b0 &
b0 +
b0 -
0(
1"
#28
0"
#29
b1 &
b1 +
b1 -
1(
1"
#30
1)
0'
b10 %
b10 ,
0"
0$
#31
1'
b11 %
b11 ,
1*
b10 &
b10 +
b10 -
0(
1"
#32
1!
0"
1$
#33
0)
0'
b0 %
b0 ,
0!
b11 &
b11 +
b11 -
1(
1"
#34
0"
#35
1'
b1 %
b1 ,
0*
b0 &
b0 +
b0 -
0(
1"
#36
0"
#37
b1 &
b1 +
b1 -
1(
1"
